{
  "animals": [
    {
      "id": 2,
      "name": "Decker",
      "breed": "German Sheperd",
      "imgLocation": "./img/dog.svg"
    },
    {
      "id": 4,
      "name": "Scooby Doo",
      "breed": "Great Dane",
      "imgLocation": "./img/scooby.jpg"
    },
    {
      "id": 5,
      "name": "Scrappy",
      "breed": "Great Dane",
      "imgLocation": "./img/scrappy.png"
    },
    {
      "id": 7,
      "name": "Lady Doo",
      "breed": "Great Dane",
      "imgLocation": "https://pbs.twimg.com/media/C_m36nVXYAABlWF.jpg"
    },
    {
      "name": "asdf",
      "breed": "sfd",
      "imgLocation": "https://www.rachaelrayshow.com/sites/default/files/styles/video_1920x1080/public/images/2019-06/dog.jpg?itok=mFEHYdZh",
      "id": 10
    },
    {
      "name": "terry",
      "breed": "pug",
      "imgLocation": "https://www.petmd.com/sites/default/files/Acute-Dog-Diarrhea-47066074.jpg",
      "id": 11
    },
    {
      "name": "Amber",
      "breed": "Dog",
      "imgLocation": "https://vignette.wikia.nocookie.net/scoobydoo/images/0/01/Amber.png/revision/latest?cb=20160117025826",
      "id": 12
    }
  ],
  "employees": [
    {
      "id": 1,
      "name": "Lamar",
      "job": "Breeder",
      "imgLocation": "./employee.svg"
    },
    {
      "id": 2,
      "name": "Kesha",
      "job": "Groomer",
      "imgLocation": "./cowgirl.svg"
    },
    {
      "id": 3,
      "name": "Linda",
      "job": "Cashier",
      "imgLocation": "./cowgirl.svg"
    },
    {
      "id": 4,
      "name": "Rodney",
      "job": "Groomer",
      "imgLocation": "./employee.svg"
    }
  ],
  "locations": [
    {
      "id": 1,
      "name": "Nashville",
      "imgLocation": "./location.jpg"
    },
    {
      "id": 2,
      "name": "The River",
      "imgLocation": "./location.jpg"
    },
    {
      "id": 3,
      "name": "The Field",
      "imgLocation": "./rickLocation.jpeg"
    }
  ],
  "owners": [
    {
      "id": 1,
      "name": "Rashawn",
      "phoneNumber": "615-222-2900",
      "imgLocation": "./owner.svg"
    },
    {
      "id": 2,
      "name": "Marcus",
      "phoneNumber": "615-222-2909",
      "imgLocation": "./owner.svg"
    },
    {
      "id": 3,
      "name": "Susan",
      "phoneNumber": "615-222-2919",
      "imgLocation": "./cowgirl.svg"
    },
    {
      "id": 4,
      "name": "Leslie",
      "phoneNumber": "615-222-2919",
      "imgLocation": "./cowgirl.svg"
    },
    {
      "id": 5,
      "name": "Paco",
      "phoneNumber": "615-222-2919",
      "imgLocation": "./owner.svg"
    }
  ]
}